{
    "election": {
        "Election": {
            "id": "54d9c635-fe9c-4921-bd18-6b30acb5b862",
            "parent_id": "550bce56-d91c-4719-b23e-379bacb5b862",
            "name": "第五選區[區域]",
            "lft": "29342",
            "rght": "29343",
            "population": "0",
            "population_electors": "0",
            "quota": "0",
            "quota_women": "0",
            "bulletin_key": null,
            "keywords": "2005-12,縣市議員,臺南市第五選區[區域]"
        },
        "Candidate": [
            {
                "id": "54d9c635-0910-49bb-ba9b-6b30acb5b862",
                "image": null,
                "stage": "2",
                "name": "郭信良",
                "party": "民主進步黨",
                "gender": "m",
                "no": "6",
                "name_english": "",
                "election_id": "54d9c635-fe9c-4921-bd18-6b30acb5b862"
            },
            {
                "id": "54d9c635-0a68-4c2f-aef0-6b30acb5b862",
                "image": null,
                "stage": "1",
                "name": "吳欽郎",
                "party": "無",
                "gender": "m",
                "no": "9",
                "name_english": "",
                "election_id": "54d9c635-fe9c-4921-bd18-6b30acb5b862"
            },
            {
                "id": "54d9c635-1a0c-4532-b2c9-6b30acb5b862",
                "image": null,
                "stage": "2",
                "name": "黃麗招",
                "party": "中國國民黨",
                "gender": "f",
                "no": "1",
                "name_english": "",
                "election_id": "54d9c635-fe9c-4921-bd18-6b30acb5b862"
            },
            {
                "id": "54d9c635-4de8-478a-b01c-6b30acb5b862",
                "image": null,
                "stage": "2",
                "name": "郭清華",
                "party": "無",
                "gender": "m",
                "no": "12",
                "name_english": "",
                "election_id": "54d9c635-fe9c-4921-bd18-6b30acb5b862"
            },
            {
                "id": "54d9c635-5d68-4403-87a1-6b30acb5b862",
                "image": null,
                "stage": "1",
                "name": "吳坤璉",
                "party": "民主進步黨",
                "gender": "m",
                "no": "8",
                "name_english": "",
                "election_id": "54d9c635-fe9c-4921-bd18-6b30acb5b862"
            },
            {
                "id": "54d9c635-6870-473b-a908-6b30acb5b862",
                "image": null,
                "stage": "1",
                "name": "吳清遊",
                "party": "無",
                "gender": "m",
                "no": "3",
                "name_english": "",
                "election_id": "54d9c635-fe9c-4921-bd18-6b30acb5b862"
            },
            {
                "id": "54d9c635-8774-4442-b4c8-6b30acb5b862",
                "image": null,
                "stage": "2",
                "name": "唐儀靜",
                "party": "民主進步黨",
                "gender": "f",
                "no": "5",
                "name_english": "",
                "election_id": "54d9c635-fe9c-4921-bd18-6b30acb5b862"
            },
            {
                "id": "54d9c635-9b74-4cd2-bdc9-6b30acb5b862",
                "image": null,
                "stage": "2",
                "name": "林炳利",
                "party": "無",
                "gender": "m",
                "no": "4",
                "name_english": "",
                "election_id": "54d9c635-fe9c-4921-bd18-6b30acb5b862"
            },
            {
                "id": "54d9c635-b034-432d-a176-6b30acb5b862",
                "image": null,
                "stage": "1",
                "name": "陳雪玲",
                "party": "無",
                "gender": "f",
                "no": "2",
                "name_english": "",
                "election_id": "54d9c635-fe9c-4921-bd18-6b30acb5b862"
            },
            {
                "id": "54d9c635-baa0-4628-a6ad-6b30acb5b862",
                "image": null,
                "stage": "2",
                "name": "李慶信",
                "party": "中國國民黨",
                "gender": "m",
                "no": "11",
                "name_english": "",
                "election_id": "54d9c635-fe9c-4921-bd18-6b30acb5b862"
            },
            {
                "id": "54d9c635-c1d0-4a71-b585-6b30acb5b862",
                "image": null,
                "stage": "2",
                "name": "李長吉",
                "party": "無",
                "gender": "m",
                "no": "10",
                "name_english": "",
                "election_id": "54d9c635-fe9c-4921-bd18-6b30acb5b862"
            },
            {
                "id": "54d9c635-ca5c-4c35-b4a6-6b30acb5b862",
                "image": null,
                "stage": "2",
                "name": "凃韶芳",
                "party": "民主進步黨",
                "gender": "f",
                "no": "13",
                "name_english": "",
                "election_id": "54d9c635-fe9c-4921-bd18-6b30acb5b862"
            },
            {
                "id": "54d9c635-daac-48c5-bb3f-6b30acb5b862",
                "image": null,
                "stage": "2",
                "name": "劉益昌",
                "party": "民主進步黨",
                "gender": "m",
                "no": "7",
                "name_english": "",
                "election_id": "54d9c635-fe9c-4921-bd18-6b30acb5b862"
            },
            {
                "id": "54d9c635-ff4c-41b1-b390-6b30acb5b862",
                "image": null,
                "stage": "1",
                "name": "陳進義",
                "party": "無",
                "gender": "m",
                "no": "14",
                "name_english": "",
                "election_id": "54d9c635-fe9c-4921-bd18-6b30acb5b862"
            }
        ],
        "Area": [

        ]
    },
    "parents": [
        {
            "Election": {
                "id": "54d9c5f9-9928-4953-9e4c-6b30acb5b862",
                "parent_id": null,
                "name": "2005-12",
                "lft": "28871",
                "rght": "29996",
                "population": "0",
                "population_electors": "0",
                "quota": "0",
                "quota_women": "0",
                "bulletin_key": null,
                "keywords": null
            }
        },
        {
            "Election": {
                "id": "54d9c619-6940-433b-897f-6b30acb5b862",
                "parent_id": "54d9c5f9-9928-4953-9e4c-6b30acb5b862",
                "name": "縣市議員",
                "lft": "28920",
                "rght": "29355",
                "population": "0",
                "population_electors": "0",
                "quota": "0",
                "quota_women": "0",
                "bulletin_key": null,
                "keywords": null
            }
        },
        {
            "Election": {
                "id": "550bce56-d91c-4719-b23e-379bacb5b862",
                "parent_id": "54d9c619-6940-433b-897f-6b30acb5b862",
                "name": "臺南市",
                "lft": "29331",
                "rght": "29344",
                "population": "0",
                "population_electors": "0",
                "quota": "0",
                "quota_women": "0",
                "bulletin_key": null,
                "keywords": null
            }
        },
        {
            "Election": {
                "id": "54d9c635-fe9c-4921-bd18-6b30acb5b862",
                "parent_id": "550bce56-d91c-4719-b23e-379bacb5b862",
                "name": "第五選區[區域]",
                "lft": "29342",
                "rght": "29343",
                "population": "0",
                "population_electors": "0",
                "quota": "0",
                "quota_women": "0",
                "bulletin_key": null,
                "keywords": "2005-12,縣市議員,臺南市第五選區[區域]"
            }
        }
    ],
    "children": [

    ]
}