{
    "election": {
        "Election": {
            "id": "54d9c488-4438-466d-b3f8-6b30acb5b862",
            "parent_id": "550bce29-028c-49aa-a5d8-379bacb5b862",
            "name": "第04選區[區域]",
            "lft": "20356",
            "rght": "20357",
            "population": "0",
            "population_electors": "0",
            "quota": "0",
            "quota_women": "0",
            "bulletin_key": null,
            "keywords": "2010-11,直轄市議員,高雄市第04選區[區域]"
        },
        "Candidate": [
            {
                "id": "54d9c488-0cd8-43b2-9a9d-6b30acb5b862",
                "image": null,
                "stage": "2",
                "name": "黃石龍",
                "party": "無黨籍及未經政黨推薦",
                "gender": "m",
                "no": "3",
                "name_english": "",
                "election_id": "54d9c488-4438-466d-b3f8-6b30acb5b862"
            },
            {
                "id": "54d9c488-30d4-46ea-b585-6b30acb5b862",
                "image": null,
                "stage": "1",
                "name": "王貴雄",
                "party": "無黨籍及未經政黨推薦",
                "gender": "m",
                "no": "5",
                "name_english": "",
                "election_id": "54d9c488-4438-466d-b3f8-6b30acb5b862"
            },
            {
                "id": "54d9c488-5168-4045-bce7-6b30acb5b862",
                "image": null,
                "stage": "1",
                "name": "藍健菖",
                "party": "台灣團結聯盟",
                "gender": "m",
                "no": "1",
                "name_english": "",
                "election_id": "54d9c488-4438-466d-b3f8-6b30acb5b862"
            },
            {
                "id": "54d9c488-cd24-47e8-87f6-6b30acb5b862",
                "image": null,
                "stage": "1",
                "name": "蔡長根",
                "party": "無黨籍及未經政黨推薦",
                "gender": "m",
                "no": "2",
                "name_english": "",
                "election_id": "54d9c488-4438-466d-b3f8-6b30acb5b862"
            },
            {
                "id": "54d9c488-e7b0-499d-8997-6b30acb5b862",
                "image": null,
                "stage": "2",
                "name": "李眉蓁",
                "party": "中國國民黨",
                "gender": "f",
                "no": "4",
                "name_english": "",
                "election_id": "54d9c488-4438-466d-b3f8-6b30acb5b862"
            },
            {
                "id": "54d9c489-0a94-4df0-a684-6b30acb5b862",
                "image": null,
                "stage": "1",
                "name": "黃昭星",
                "party": "民主進步黨",
                "gender": "m",
                "no": "9",
                "name_english": "",
                "election_id": "54d9c488-4438-466d-b3f8-6b30acb5b862"
            },
            {
                "id": "54d9c489-13a8-4296-aa15-6b30acb5b862",
                "image": null,
                "stage": "2",
                "name": "林瑩蓉",
                "party": "民主進步黨",
                "gender": "f",
                "no": "13",
                "name_english": "",
                "election_id": "54d9c488-4438-466d-b3f8-6b30acb5b862"
            },
            {
                "id": "54d9c489-2988-4447-817d-6b30acb5b862",
                "image": null,
                "stage": "1",
                "name": "楊統一",
                "party": "無黨籍及未經政黨推薦",
                "gender": "m",
                "no": "11",
                "name_english": "",
                "election_id": "54d9c488-4438-466d-b3f8-6b30acb5b862"
            },
            {
                "id": "54d9c489-6280-43a0-9e88-6b30acb5b862",
                "image": null,
                "stage": "2",
                "name": "張豐藤",
                "party": "民主進步黨",
                "gender": "m",
                "no": "7",
                "name_english": "",
                "election_id": "54d9c488-4438-466d-b3f8-6b30acb5b862"
            },
            {
                "id": "54d9c489-684c-4fd2-a467-6b30acb5b862",
                "image": null,
                "stage": "2",
                "name": "周鍾㴴",
                "party": "中國國民黨",
                "gender": "m",
                "no": "12",
                "name_english": "",
                "election_id": "54d9c488-4438-466d-b3f8-6b30acb5b862"
            },
            {
                "id": "54d9c489-6b14-4657-8d0f-6b30acb5b862",
                "image": null,
                "stage": "2",
                "name": "藍星木",
                "party": "中國國民黨",
                "gender": "m",
                "no": "8",
                "name_english": "",
                "election_id": "54d9c488-4438-466d-b3f8-6b30acb5b862"
            },
            {
                "id": "54d9c489-8374-4f78-a74b-6b30acb5b862",
                "image": null,
                "stage": "2",
                "name": "陳玫娟",
                "party": "中國國民黨",
                "gender": "f",
                "no": "10",
                "name_english": "",
                "election_id": "54d9c488-4438-466d-b3f8-6b30acb5b862"
            },
            {
                "id": "54d9c489-e428-4a61-b609-6b30acb5b862",
                "image": null,
                "stage": "2",
                "name": "陳麗珍",
                "party": "中國國民黨",
                "gender": "f",
                "no": "6",
                "name_english": "",
                "election_id": "54d9c488-4438-466d-b3f8-6b30acb5b862"
            }
        ],
        "Area": []
    },
    "parents": [
        {
            "Election": {
                "id": "54d9c47d-8b20-4f23-b931-6b30acb5b862",
                "parent_id": null,
                "name": "2010-11",
                "lft": "20223",
                "rght": "27902",
                "population": "0",
                "population_electors": "0",
                "quota": "0",
                "quota_women": "0",
                "bulletin_key": null,
                "keywords": null
            }
        },
        {
            "Election": {
                "id": "54d9c47f-50d0-4cb2-a7bf-6b30acb5b862",
                "parent_id": "54d9c47d-8b20-4f23-b931-6b30acb5b862",
                "name": "直轄市議員",
                "lft": "20236",
                "rght": "20385",
                "population": "0",
                "population_electors": "0",
                "quota": "0",
                "quota_women": "0",
                "bulletin_key": null,
                "keywords": null
            }
        },
        {
            "Election": {
                "id": "550bce29-028c-49aa-a5d8-379bacb5b862",
                "parent_id": "54d9c47f-50d0-4cb2-a7bf-6b30acb5b862",
                "name": "高雄市",
                "lft": "20353",
                "rght": "20384",
                "population": "0",
                "population_electors": "0",
                "quota": "0",
                "quota_women": "0",
                "bulletin_key": null,
                "keywords": null
            }
        },
        {
            "Election": {
                "id": "54d9c488-4438-466d-b3f8-6b30acb5b862",
                "parent_id": "550bce29-028c-49aa-a5d8-379bacb5b862",
                "name": "第04選區[區域]",
                "lft": "20356",
                "rght": "20357",
                "population": "0",
                "population_electors": "0",
                "quota": "0",
                "quota_women": "0",
                "bulletin_key": null,
                "keywords": "2010-11,直轄市議員,高雄市第04選區[區域]"
            }
        }
    ],
    "children": []
}