{
    "election": {
        "Election": {
            "id": "53c024e3-db94-43fa-8607-5c5aacb5b862",
            "parent_id": "53c024de-9698-4687-9de0-5c5aacb5b862",
            "name": "中興里",
            "lft": "15707",
            "rght": "15708",
            "population": "7337",
            "population_electors": "6243",
            "quota": "1",
            "quota_women": "0",
            "bulletin_key": "546f277e-1468-4f68-936d-2f28cf91e152",
            "keywords": "2014-11,村里長,新北市,汐止區,中興里"
        },
        "Candidate": [
            {
                "id": "53c026ce-4154-4d1c-9b5a-5dffacb5b862",
                "image": null,
                "stage": "1",
                "name": "高辰雨",
                "party": "中國國民黨",
                "gender": "m",
                "no": "1",
                "name_english": "KAO DAVID",
                "election_id": "53c024e3-db94-43fa-8607-5c5aacb5b862"
            },
            {
                "id": "540b535d-2fcc-4658-8306-1926acb5b862",
                "image": null,
                "stage": "1",
                "name": "羅文義",
                "party": "無",
                "gender": "m",
                "no": "2",
                "name_english": "LO WENYI",
                "election_id": "53c024e3-db94-43fa-8607-5c5aacb5b862"
            },
            {
                "id": "540b535d-9ccc-4c5a-84ba-1926acb5b862",
                "image": null,
                "stage": "1",
                "name": "賴黃金玉",
                "party": "民主進步黨",
                "gender": "f",
                "no": "4",
                "name_english": "LAI HUANG CHIN YU",
                "election_id": "53c024e3-db94-43fa-8607-5c5aacb5b862"
            },
            {
                "id": "540b535d-bebc-467d-b138-1926acb5b862",
                "image": null,
                "stage": "2",
                "name": "蔡振國",
                "party": "無",
                "gender": "m",
                "no": "5",
                "name_english": "",
                "election_id": "53c024e3-db94-43fa-8607-5c5aacb5b862"
            },
            {
                "id": "540b535d-d448-4f54-9ccd-1926acb5b862",
                "image": "546e367b\/20cc\/4494\/8498\/52118e043389.jpg",
                "stage": "1",
                "name": "鄭麗秋",
                "party": "無",
                "gender": "f",
                "no": "3",
                "name_english": "CHENG LI CHIU",
                "election_id": "53c024e3-db94-43fa-8607-5c5aacb5b862"
            }
        ],
        "Area": [
            {
                "id": "53c01f35-edd4-44ed-ae7a-5460acb5b862",
                "name": "中興里",
                "is_area": true,
                "keywords": "2014,新北市,汐止區,中興里",
                "AreasElection": {
                    "id": "53c024e3-7d2c-44bf-828f-5c5aacb5b862",
                    "Election_id": "53c024e3-db94-43fa-8607-5c5aacb5b862",
                    "Area_id": "53c01f35-edd4-44ed-ae7a-5460acb5b862"
                }
            }
        ]
    },
    "parents": [
        {
            "Election": {
                "id": "53c0202e-79d4-44a1-99d3-5460acb5b862",
                "parent_id": null,
                "name": "2014-11",
                "lft": "1",
                "rght": "19276",
                "population": "0",
                "population_electors": "0",
                "quota": "1",
                "quota_women": "0",
                "bulletin_key": null,
                "keywords": null
            }
        },
        {
            "Election": {
                "id": "53c02030-eab8-4960-a0d6-5460acb5b862",
                "parent_id": "53c0202e-79d4-44a1-99d3-5460acb5b862",
                "name": "村里長",
                "lft": "2786",
                "rght": "19275",
                "population": "0",
                "population_electors": "0",
                "quota": "1",
                "quota_women": "0",
                "bulletin_key": null,
                "keywords": null
            }
        },
        {
            "Election": {
                "id": "53c0246c-81d4-4b72-933c-5c5aacb5b862",
                "parent_id": "53c02030-eab8-4960-a0d6-5460acb5b862",
                "name": "新北市",
                "lft": "14261",
                "rght": "16384",
                "population": "0",
                "population_electors": "0",
                "quota": "1",
                "quota_women": "0",
                "bulletin_key": null,
                "keywords": null
            }
        },
        {
            "Election": {
                "id": "53c024de-9698-4687-9de0-5c5aacb5b862",
                "parent_id": "53c0246c-81d4-4b72-933c-5c5aacb5b862",
                "name": "汐止區",
                "lft": "15652",
                "rght": "15753",
                "population": "0",
                "population_electors": "0",
                "quota": "1",
                "quota_women": "0",
                "bulletin_key": null,
                "keywords": null
            }
        },
        {
            "Election": {
                "id": "53c024e3-db94-43fa-8607-5c5aacb5b862",
                "parent_id": "53c024de-9698-4687-9de0-5c5aacb5b862",
                "name": "中興里",
                "lft": "15707",
                "rght": "15708",
                "population": "7337",
                "population_electors": "6243",
                "quota": "1",
                "quota_women": "0",
                "bulletin_key": "546f277e-1468-4f68-936d-2f28cf91e152",
                "keywords": "2014-11,村里長,新北市,汐止區,中興里"
            }
        }
    ],
    "children": []
}