{
    "candidate": {
        "Candidate": {
            "id": "53c028ac-6778-47fb-9ede-5dffacb5b862",
            "election_id": "\u0000\u0000\u0000\u0000\u0000\u0000\u0000\u0000\u0000\u0000\u0000\u0000\u0000\u0000\u0000\u0000\u0000\u0000\u0000\u0000\u0000\u0000\u0000\u0000\u0000\u0000\u0000\u0000\u0000\u0000\u0000\u0000\u0000\u0000\u0000\u0000",
            "is_reviewed": true,
            "active_id": null,
            "stage": "0",
            "vote_count": "0",
            "name": "黃永富",
            "image": null,
            "party": null,
            "contacts_phone": null,
            "contacts_fax": null,
            "contacts_email": null,
            "contacts_address": null,
            "links": null,
            "gender": null,
            "no": "0",
            "education_level": "",
            "is_present": false,
            "name_english": "",
            "birth_place": "",
            "birth": null,
            "platform": "",
            "education": null,
            "experience": null,
            "created": "0000-00-00 00:00:00",
            "modified": "0000-00-00 00:00:00"
        },
        "Election": {
            "id": null,
            "population_electors": null,
            "population": null,
            "quota": null,
            "quota_women": null,
            "bulletin_key": null
        },
        "Tag": [

        ]
    },
    "parents": null
}