{
    "election": {
        "Election": {
            "id": "53c02089-f1bc-40f3-b766-5c5aacb5b862",
            "parent_id": "53c02087-d634-4ed1-947c-5c5aacb5b862",
            "name": "五結鄉",
            "lft": "650",
            "rght": "651",
            "population": "39332",
            "population_electors": "32513",
            "quota": "1",
            "quota_women": "0",
            "bulletin_key": "546eb71f-cf58-405e-a074-2adbcf91e152",
            "keywords": "2014-11,鄉鎮市長,宜蘭縣,五結鄉"
        },
        "Candidate": [
            {
                "id": "5406a5fd-0d50-4d3e-abfe-15b8acb5b862",
                "image": "54942672\/07bc\/41c1\/8025\/37846ab936af.jpg",
                "stage": "2",
                "name": "簡松樹",
                "party": "民主進步黨",
                "gender": "m",
                "no": "1",
                "name_english": "CHIEN SUNG SHU",
                "election_id": "53c02089-f1bc-40f3-b766-5c5aacb5b862"
            },
            {
                "id": "540b581b-dcec-4900-904e-1926acb5b862",
                "image": "549426a3\/ecc4\/4b67\/9dd6\/378a6ab936af.jpg",
                "stage": "1",
                "name": "林義剛",
                "party": "中國國民黨",
                "gender": "m",
                "no": "2",
                "name_english": "LIN I KAN",
                "election_id": "53c02089-f1bc-40f3-b766-5c5aacb5b862"
            }
        ],
        "Area": [
            {
                "id": "53c01bef-fbfc-41ab-8f6e-5460acb5b862",
                "name": "五結鄉",
                "is_area": true,
                "keywords": "2014,宜蘭縣,五結鄉",
                "AreasElection": {
                    "id": "53c02089-5280-4b50-b2c2-5c5aacb5b862",
                    "Election_id": "53c02089-f1bc-40f3-b766-5c5aacb5b862",
                    "Area_id": "53c01bef-fbfc-41ab-8f6e-5460acb5b862"
                }
            }
        ]
    },
    "parents": [
        {
            "Election": {
                "id": "53c0202e-79d4-44a1-99d3-5460acb5b862",
                "parent_id": null,
                "name": "2014-11",
                "lft": "1",
                "rght": "19276",
                "population": "0",
                "population_electors": "0",
                "quota": "1",
                "quota_women": "0",
                "bulletin_key": null,
                "keywords": null
            }
        },
        {
            "Election": {
                "id": "53c02030-49d0-4613-be8a-5460acb5b862",
                "parent_id": "53c0202e-79d4-44a1-99d3-5460acb5b862",
                "name": "鄉鎮市長",
                "lft": "608",
                "rght": "1031",
                "population": "0",
                "population_electors": "0",
                "quota": "1",
                "quota_women": "0",
                "bulletin_key": null,
                "keywords": null
            }
        },
        {
            "Election": {
                "id": "53c02087-d634-4ed1-947c-5c5aacb5b862",
                "parent_id": "53c02030-49d0-4613-be8a-5460acb5b862",
                "name": "宜蘭縣",
                "lft": "633",
                "rght": "658",
                "population": "0",
                "population_electors": "0",
                "quota": "1",
                "quota_women": "0",
                "bulletin_key": null,
                "keywords": null
            }
        },
        {
            "Election": {
                "id": "53c02089-f1bc-40f3-b766-5c5aacb5b862",
                "parent_id": "53c02087-d634-4ed1-947c-5c5aacb5b862",
                "name": "五結鄉",
                "lft": "650",
                "rght": "651",
                "population": "39332",
                "population_electors": "32513",
                "quota": "1",
                "quota_women": "0",
                "bulletin_key": "546eb71f-cf58-405e-a074-2adbcf91e152",
                "keywords": "2014-11,鄉鎮市長,宜蘭縣,五結鄉"
            }
        }
    ],
    "children": []
}