{
    "candidate": {
        "Candidate": {
            "id": "53c027fd-5bc4-48b3-8801-5dffacb5b862",
            "election_id": "53c021ee-4e64-4d8b-8b75-5c5aacb5b862",
            "is_reviewed": true,
            "active_id": null,
            "stage": "2",
            "vote_count": "937",
            "name": "張欽堂",
            "image": null,
            "party": "中國國民黨",
            "contacts_phone": null,
            "contacts_fax": null,
            "contacts_email": null,
            "contacts_address": null,
            "links": null,
            "gender": "m",
            "no": "1",
            "education_level": "高中",
            "is_present": false,
            "name_english": "CHANG CHING TANG",
            "birth_place": "臺灣省",
            "birth": "1953-11-09",
            "platform": "",
            "education": null,
            "experience": null,
            "created": "0000-00-00 00:00:00",
            "modified": "2015-02-08 23:44:59"
        },
        "Election": {
            "id": "53c021ee-4e64-4d8b-8b75-5c5aacb5b862",
            "population_electors": "2729",
            "population": "3593",
            "quota": "1",
            "quota_women": "0",
            "bulletin_key": "546ec076-28ac-4de8-ad5e-2d4fcf91e152",
            "Area": [
                {
                    "id": "53c01ce9-b40c-4854-bdd8-5460acb5b862",
                    "name": "鎮北里",
                    "AreasElection": {
                        "id": "53c021ee-1494-49b1-839e-5c5aacb5b862",
                        "Election_id": "53c021ee-4e64-4d8b-8b75-5c5aacb5b862",
                        "Area_id": "53c01ce9-b40c-4854-bdd8-5460acb5b862"
                    }
                }
            ]
        },
        "Tag": [

        ]
    },
    "parents": [
        {
            "Election": {
                "id": "53c0202e-79d4-44a1-99d3-5460acb5b862",
                "parent_id": null,
                "name": "2014-11",
                "lft": "1",
                "rght": "19276",
                "population": "0",
                "population_electors": "0",
                "quota": "1",
                "quota_women": "0",
                "bulletin_key": null,
                "keywords": null
            }
        },
        {
            "Election": {
                "id": "53c02030-eab8-4960-a0d6-5460acb5b862",
                "parent_id": "53c0202e-79d4-44a1-99d3-5460acb5b862",
                "name": "村里長",
                "lft": "2786",
                "rght": "19275",
                "population": "0",
                "population_electors": "0",
                "quota": "1",
                "quota_women": "0",
                "bulletin_key": null,
                "keywords": null
            }
        },
        {
            "Election": {
                "id": "53c021ec-e11c-49be-b6c8-5c5aacb5b862",
                "parent_id": "53c02030-eab8-4960-a0d6-5460acb5b862",
                "name": "雲林縣",
                "lft": "6201",
                "rght": "7018",
                "population": "0",
                "population_electors": "0",
                "quota": "1",
                "quota_women": "0",
                "bulletin_key": null,
                "keywords": null
            }
        },
        {
            "Election": {
                "id": "53c021ec-e218-48e1-a17c-5c5aacb5b862",
                "parent_id": "53c021ec-e11c-49be-b6c8-5c5aacb5b862",
                "name": "斗六市",
                "lft": "6202",
                "rght": "6279",
                "population": "0",
                "population_electors": "0",
                "quota": "1",
                "quota_women": "0",
                "bulletin_key": null,
                "keywords": null
            }
        },
        {
            "Election": {
                "id": "53c021ee-4e64-4d8b-8b75-5c5aacb5b862",
                "parent_id": "53c021ec-e218-48e1-a17c-5c5aacb5b862",
                "name": "鎮北里",
                "lft": "6229",
                "rght": "6230",
                "population": "3593",
                "population_electors": "2729",
                "quota": "1",
                "quota_women": "0",
                "bulletin_key": "546ec076-28ac-4de8-ad5e-2d4fcf91e152",
                "keywords": "2014-11,村里長,雲林縣,斗六市,鎮北里"
            }
        }
    ]
}